[
    {
        "title": "Bericht 3",
        "date": "vrijdag 26 februari",
        "content": "Dit is het nieuwste bericht                ",
        "author_name": "Tiago"
    },
    {
        "title": "test",
        "date": "test",
        "content": "test                ",
        "author_name": "test"
    },
    {
        "title": "test",
        "date": "test",
        "content": "test                ",
        "author_name": "test"
    },
    {
        "title": "help",
        "date": "help",
        "content": "help                ",
        "author_name": "help"
    },
    {
        "title": "new",
        "date": "new",
        "content": "new                ",
        "author_name": "new"
    },
    {
        "title": "new",
        "date": "new",
        "content": "new                ",
        "author_name": "new"
    },
    {
        "title": "new",
        "date": "new",
        "content": "new                ",
        "author_name": "new"
    },
    {
        "title": "new",
        "date": "new",
        "content": "new                ",
        "author_name": "new"
    },
    {
        "title": "newpost",
        "date": "newpost",
        "content": "newpost   ",
        "author_name": "newpost"
    },
    {
        "title": "xyz",
        "date": "xyz",
        "content": "xyz                ",
        "author_name": "xyz"
    },
    {
        "title": "xyz",
        "date": "xyz",
        "content": "xyz                ",
        "author_name": "xyz"
    },
    {
        "title": "Nieuw bericht ",
        "date": "Maandag 1 maart 2021",
        "content": "Eindelijk begint het op iets te trekken                ",
        "author_name": "Pedrito"
    },
    {
        "title": "Test reverse",
        "date": "26\/02\/2021",
        "content": "show items in reversed order                ",
        "author_name": "Pedrito"
    }
]